examples/data_logger.py
examples/shared_memory_array.py
ataraxis_data_structures/__init__.py
ataraxis_data_structures/py.typed
ataraxis_data_structures/data_loggers/__init__.py
ataraxis_data_structures/data_loggers/serialized_data_logger.py
ataraxis_data_structures/data_structures/__init__.py
ataraxis_data_structures/data_structures/yaml_config.py
ataraxis_data_structures/shared_memory/__init__.py
ataraxis_data_structures/shared_memory/shared_memory_array.py
ataraxis_data_structures-5.0.0.dist-info/METADATA
ataraxis_data_structures-5.0.0.dist-info/WHEEL
ataraxis_data_structures-5.0.0.dist-info/licenses/LICENSE
ataraxis_data_structures-5.0.0.dist-info/RECORD
