Metadata-Version: 2.4
Name: ataraxis-data-structures
Version: 5.0.0
Summary: Provides classes and structures for storing, manipulating, and sharing data between Python processes.
Project-URL: Homepage, https://github.com/Sun-Lab-NBB/ataraxis-data-structures
Project-URL: Documentation, https://ataraxis-data-structures-api-docs.netlify.app/
Author-email: Ivan Kondratyev <ik278@cornell.edu>
Maintainer-email: Ivan Kondratyev <ik278@cornell.edu>
License:                     GNU GENERAL PUBLIC LICENSE
License-File: LICENSE
Keywords: ataraxis,data logging,data manipulation,data structures,shared memory
Classifier: Development Status :: 5 - Production/Stable
Classifier: Intended Audience :: Developers
Classifier: License :: OSI Approved :: GNU General Public License v3 or later (GPLv3+)
Classifier: Operating System :: MacOS :: MacOS X
Classifier: Operating System :: Microsoft :: Windows
Classifier: Operating System :: POSIX :: Linux
Classifier: Programming Language :: Python :: 3.12
Classifier: Programming Language :: Python :: 3.13
Classifier: Programming Language :: Python :: 3.14
Classifier: Topic :: Software Development
Classifier: Typing :: Typed
Requires-Python: <3.15,>=3.12
Requires-Dist: ataraxis-base-utilities<6,>=5
Requires-Dist: ataraxis-time<6,>=5
Requires-Dist: dacite<2,>=1
Requires-Dist: numpy<3,>=2
Requires-Dist: pyyaml<7,>=6
Requires-Dist: tqdm<5,>=4
Provides-Extra: dev
Requires-Dist: ataraxis-automation<8,>=7; extra == 'dev'
Requires-Dist: tox-uv<2,>=1; extra == 'dev'
Requires-Dist: tox<5,>=4; extra == 'dev'
Requires-Dist: types-pyyaml<7,>=6; extra == 'dev'
Requires-Dist: types-tqdm<5,>=4; extra == 'dev'
Requires-Dist: uv<1,>=0; extra == 'dev'
